<?xml version="1.0" encoding="UTF-8"?>
<objects serializationModel="Studio.02.03.00">
	<object class="AudioFile" id="{1d35bff2-73d5-4c84-aaf3-a7af892f63d7}">
		<property name="assetPath">
			<value>SFX/Ambient/Room Ambience/LightFlicker01.ogg</value>
		</property>
		<property name="frequencyInKHz">
			<value>44.0999985</value>
		</property>
		<property name="channelCount">
			<value>2</value>
		</property>
		<property name="length">
			<value>6</value>
		</property>
		<relationship name="masterAssetFolder">
			<destination>{bb207cbb-91a3-438a-8739-c083dc59e2e5}</destination>
		</relationship>
	</object>
</objects>
